{
  "TAP": "shop/submit",
  "name": "后海科兴总店",
  "shopLevel": 2,
  "posBaseUrl": "https://area53-win.pospal.cn:443/",
  "posAppId": "747A09332D58D135805F190A93C84FA7",
  "posAppSecret": "874859095189735996",
  "opETime": 0,
  "opSTime": 10000,
  "adrArea1": "44",
  "adrArea2": "4403",
  "adrArea3": "440305",
  "adrDetail": "后海科技大道",
  "avatarImg": "@img",
  "bigImg": "@img",
  "bk": {
    "bankName": "平安银行后海支行",
    "city": "深圳",
    "num": "62033018234248",
    "userName": "莫文业"
  },
  "childIds": [

  ],
  "com": {
    "comAddr": "后台中科大厦",
    "comCode": "3423432429",
    "comLicense": "@img",
    "comLpIdCardNum": "440437199102311",
    "comName": "文兴果业",
    "comOpRange": "零售、餐饮"
  },
  "commissionRate": 0.05,
  "cpMobile": "13800384234",
  "cpName": "莫文业",
  "cpTel": "0755-5433138",
  "description": "新媒体零售体",
  "latitude": 180.32,
  "longitude": 22.31,
  "lp": {
    "lpIdCardBack": "@img",
    "lpIdCardFront": "@img",
    "lpIdCardNum": "440437199102311",
    "lpMobile": "13800384234",
    "lpName": "莫文业"
  },
  "ls": {
    "shopCode": "823423484289293",
    "shopLicense": "@img",
    "shopOpRange": "水果、零食"
  },
  "sbk": {
    "bankName": "中国银行福田支行",
    "city": "深圳",
    "num": "62391083489728942",
    "userName": "莫文业"
  }
}