<?xml version="1.0" encoding="UTF-8"?>
<!DOCTYPE mapper PUBLIC "-//mybatis.org//DTD Mapper 3.0//EN" "http://mybatis.org/dtd/mybatis-3-mapper.dtd">
<mapper namespace="com.verificer.biz.biz.mapper.AddrMapper">
  <resultMap id="BaseResultMap" type="com.verificer.biz.biz.entity.Addr">
    <!--
      WARNING - @mbg.generated
      This element is automatically generated by MyBatis Generator, do not modify.
    -->
    <id column="id" jdbcType="BIGINT" property="id" />
    <result column="addr" jdbcType="VARCHAR" property="addr" />
    <result column="user_id" jdbcType="VARCHAR" property="userId" />
    <result column="detail_addr" jdbcType="VARCHAR" property="detailAddr" />
    <result column="longitude" jdbcType="DECIMAL" property="longitude" />
    <result column="latitude" jdbcType="DECIMAL" property="latitude" />
    <result column="tag" jdbcType="VARCHAR" property="tag" />
    <result column="mobile" jdbcType="VARCHAR" property="mobile" />
    <result column="rc_name" jdbcType="VARCHAR" property="rcName" />
    <result column="create_time" jdbcType="BIGINT" property="createTime" />
  </resultMap>
  <sql id="Base_Column_List">
    <!--
      WARNING - @mbg.generated
      This element is automatically generated by MyBatis Generator, do not modify.
    -->
    id, addr, user_id, detail_addr, longitude, latitude, tag, mobile, rc_name, create_time
  </sql>
  <select id="selectByPrimaryKey" parameterType="java.lang.Long" resultMap="BaseResultMap">
    <!--
      WARNING - @mbg.generated
      This element is automatically generated by MyBatis Generator, do not modify.
    -->
    select 
    <include refid="Base_Column_List" />
    from addr
    where id = #{id,jdbcType=BIGINT}
  </select>
  <delete id="deleteByPrimaryKey" parameterType="java.lang.Long">
    <!--
      WARNING - @mbg.generated
      This element is automatically generated by MyBatis Generator, do not modify.
    -->
    delete from addr
    where id = #{id,jdbcType=BIGINT}
  </delete>
  <insert id="insert" parameterType="com.verificer.biz.biz.entity.Addr">
    <!--
      WARNING - @mbg.generated
      This element is automatically generated by MyBatis Generator, do not modify.
    -->
    <selectKey keyProperty="id" order="AFTER" resultType="java.lang.Long">
      SELECT LAST_INSERT_ID()
    </selectKey>
    insert into addr (addr, user_id, detail_addr, 
      longitude, latitude, tag, 
      mobile, rc_name, create_time
      )
    values (#{addr,jdbcType=VARCHAR}, #{userId,jdbcType=VARCHAR}, #{detailAddr,jdbcType=VARCHAR}, 
      #{longitude,jdbcType=DECIMAL}, #{latitude,jdbcType=DECIMAL}, #{tag,jdbcType=VARCHAR}, 
      #{mobile,jdbcType=VARCHAR}, #{rcName,jdbcType=VARCHAR}, #{createTime,jdbcType=BIGINT}
      )
  </insert>
  <insert id="insertSelective" parameterType="com.verificer.biz.biz.entity.Addr">
    <!--
      WARNING - @mbg.generated
      This element is automatically generated by MyBatis Generator, do not modify.
    -->
    <selectKey keyProperty="id" order="AFTER" resultType="java.lang.Long">
      SELECT LAST_INSERT_ID()
    </selectKey>
    insert into addr
    <trim prefix="(" suffix=")" suffixOverrides=",">
      <if test="addr != null">
        addr,
      </if>
      <if test="userId != null">
        user_id,
      </if>
      <if test="detailAddr != null">
        detail_addr,
      </if>
      <if test="longitude != null">
        longitude,
      </if>
      <if test="latitude != null">
        latitude,
      </if>
      <if test="tag != null">
        tag,
      </if>
      <if test="mobile != null">
        mobile,
      </if>
      <if test="rcName != null">
        rc_name,
      </if>
      <if test="createTime != null">
        create_time,
      </if>
    </trim>
    <trim prefix="values (" suffix=")" suffixOverrides=",">
      <if test="addr != null">
        #{addr,jdbcType=VARCHAR},
      </if>
      <if test="userId != null">
        #{userId,jdbcType=VARCHAR},
      </if>
      <if test="detailAddr != null">
        #{detailAddr,jdbcType=VARCHAR},
      </if>
      <if test="longitude != null">
        #{longitude,jdbcType=DECIMAL},
      </if>
      <if test="latitude != null">
        #{latitude,jdbcType=DECIMAL},
      </if>
      <if test="tag != null">
        #{tag,jdbcType=VARCHAR},
      </if>
      <if test="mobile != null">
        #{mobile,jdbcType=VARCHAR},
      </if>
      <if test="rcName != null">
        #{rcName,jdbcType=VARCHAR},
      </if>
      <if test="createTime != null">
        #{createTime,jdbcType=BIGINT},
      </if>
    </trim>
  </insert>
  <update id="updateByPrimaryKeySelective" parameterType="com.verificer.biz.biz.entity.Addr">
    <!--
      WARNING - @mbg.generated
      This element is automatically generated by MyBatis Generator, do not modify.
    -->
    update addr
    <set>
      <if test="addr != null">
        addr = #{addr,jdbcType=VARCHAR},
      </if>
      <if test="userId != null">
        user_id = #{userId,jdbcType=VARCHAR},
      </if>
      <if test="detailAddr != null">
        detail_addr = #{detailAddr,jdbcType=VARCHAR},
      </if>
      <if test="longitude != null">
        longitude = #{longitude,jdbcType=DECIMAL},
      </if>
      <if test="latitude != null">
        latitude = #{latitude,jdbcType=DECIMAL},
      </if>
      <if test="tag != null">
        tag = #{tag,jdbcType=VARCHAR},
      </if>
      <if test="mobile != null">
        mobile = #{mobile,jdbcType=VARCHAR},
      </if>
      <if test="rcName != null">
        rc_name = #{rcName,jdbcType=VARCHAR},
      </if>
      <if test="createTime != null">
        create_time = #{createTime,jdbcType=BIGINT},
      </if>
    </set>
    where id = #{id,jdbcType=BIGINT}
  </update>
  <update id="updateByPrimaryKey" parameterType="com.verificer.biz.biz.entity.Addr">
    <!--
      WARNING - @mbg.generated
      This element is automatically generated by MyBatis Generator, do not modify.
    -->
    update addr
    set addr = #{addr,jdbcType=VARCHAR},
      user_id = #{userId,jdbcType=VARCHAR},
      detail_addr = #{detailAddr,jdbcType=VARCHAR},
      longitude = #{longitude,jdbcType=DECIMAL},
      latitude = #{latitude,jdbcType=DECIMAL},
      tag = #{tag,jdbcType=VARCHAR},
      mobile = #{mobile,jdbcType=VARCHAR},
      rc_name = #{rcName,jdbcType=VARCHAR},
      create_time = #{createTime,jdbcType=BIGINT}
    where id = #{id,jdbcType=BIGINT}
  </update>
</mapper>
